Metadata-Version: 1.1
Name: dask-funk
Version: 0.9.1
Summary: Composable keyword function graphs
Home-page: http://github.com/Savvysherpa/dask-funk
Author: Ben Mabey
Author-email: ben@benmabey.com
License: MIT
Platform: UNKNOWN
Classifier: Development Status :: 4 - Beta
Classifier: License :: OSI Approved :: MIT License
Classifier: Programming Language :: Python :: 3.4
